{
    "info": {
        "代碼": "034542",
        "學校名稱": "市立慈文國中",
        "公\/私立": "公立",
        "縣市名稱": "[03]桃園市",
        "地址": "[330]桃園市桃園區中正路835號",
        "電話": "(03)3269340",
        "網址": "http:\/\/www.twjh.tyc.edu.tw"
    },
    "tree": {
        "鳳凰木": [
            [
                121.301606,
                25.009538
            ]
        ],
        "大王椰子": [
            [
                121.301733,
                25.009204
            ],
            [
                121.301571,
                25.009606
            ],
            [
                121.301542,
                25.009658
            ],
            [
                121.301513,
                25.00971
            ],
            [
                121.301479,
                25.009773
            ],
            [
                121.301432,
                25.009819
            ],
            [
                121.301414,
                25.009891
            ],
            [
                121.301776,
                25.009171
            ],
            [
                121.301799,
                25.009121
            ],
            [
                121.301819,
                25.009075
            ],
            [
                121.301837,
                25.009038
            ]
        ],
        "樟樹": [
            [
                121.301298,
                25.009219
            ],
            [
                121.301714,
                25.009191
            ]
        ],
        "榔榆\/紅雞油": [
            [
                121.301729,
                25.009196
            ],
            [
                121.301736,
                25.009147
            ],
            [
                121.301751,
                25.009157
            ],
            [
                121.301803,
                25.0091
            ],
            [
                121.301796,
                25.009064
            ],
            [
                121.301815,
                25.009078
            ],
            [
                121.301284,
                25.009054
            ],
            [
                121.301809,
                25.009035
            ]
        ],
        "棍棒椰子": [
            [
                121.301282,
                25.009234
            ],
            [
                121.301396,
                25.009099
            ],
            [
                121.30101,
                25.009126
            ]
        ],
        "黑板樹": [
            [
                121.301721,
                25.009176
            ],
            [
                121.301103,
                25.009958
            ],
            [
                121.30109,
                25.009934
            ],
            [
                121.301072,
                25.00992
            ],
            [
                121.301047,
                25.009899
            ],
            [
                121.301024,
                25.008952
            ],
            [
                121.301518,
                25.009475
            ],
            [
                121.301446,
                25.009485
            ],
            [
                121.30148,
                25.009546
            ],
            [
                121.301411,
                25.009555
            ],
            [
                121.301451,
                25.009598
            ],
            [
                121.301386,
                25.009612
            ],
            [
                121.301425,
                25.009652
            ],
            [
                121.301405,
                25.009688
            ],
            [
                121.301394,
                25.009703
            ],
            [
                121.30137,
                25.009658
            ],
            [
                121.301364,
                25.009674
            ],
            [
                121.301011,
                25.008985
            ],
            [
                121.300975,
                25.009041
            ],
            [
                121.300955,
                25.009077
            ],
            [
                121.300939,
                25.0091
            ],
            [
                121.300722,
                25.008999
            ],
            [
                121.300636,
                25.009041
            ],
            [
                121.300658,
                25.00917
            ],
            [
                121.300601,
                25.009144
            ],
            [
                121.300562,
                25.009232
            ],
            [
                121.301235,
                25.009243
            ],
            [
                121.300684,
                25.009094
            ],
            [
                121.30075,
                25.008904
            ],
            [
                121.300769,
                25.008858
            ],
            [
                121.300787,
                25.008806
            ]
        ],
        "榕樹\/正榕": [
            [
                121.301728,
                25.00916
            ],
            [
                121.301753,
                25.009127
            ],
            [
                121.301778,
                25.009136
            ],
            [
                121.301768,
                25.009086
            ],
            [
                121.301801,
                25.00905
            ],
            [
                121.301782,
                25.009053
            ],
            [
                121.301804,
                25.009017
            ],
            [
                121.301854,
                25.008983
            ],
            [
                121.301126,
                25.008993
            ],
            [
                121.301296,
                25.008697
            ],
            [
                121.301082,
                25.008627
            ],
            [
                121.301054,
                25.008615
            ],
            [
                121.300974,
                25.008676
            ],
            [
                121.300991,
                25.008631
            ],
            [
                121.300974,
                25.008599
            ],
            [
                121.301386,
                25.009716
            ],
            [
                121.301355,
                25.009692
            ],
            [
                121.301399,
                25.009673
            ],
            [
                121.300945,
                25.008361
            ],
            [
                121.300933,
                25.008267
            ],
            [
                121.300681,
                25.008407
            ],
            [
                121.300759,
                25.00837
            ],
            [
                121.301066,
                25.009151
            ],
            [
                121.300161,
                25.008579
            ],
            [
                121.300263,
                25.008538
            ],
            [
                121.300201,
                25.008546
            ],
            [
                121.300103,
                25.008567
            ],
            [
                121.299916,
                25.008793
            ],
            [
                121.300004,
                25.008661
            ],
            [
                121.299978,
                25.008701
            ],
            [
                121.299954,
                25.008732
            ],
            [
                121.300615,
                25.009238
            ],
            [
                121.299935,
                25.008765
            ],
            [
                121.29981,
                25.008989
            ],
            [
                121.300556,
                25.009071
            ],
            [
                121.299819,
                25.008961
            ],
            [
                121.30052,
                25.009153
            ],
            [
                121.29983,
                25.008924
            ],
            [
                121.300498,
                25.009217
            ],
            [
                121.299829,
                25.009063
            ],
            [
                121.300719,
                25.008872
            ],
            [
                121.300737,
                25.008819
            ],
            [
                121.300761,
                25.008774
            ]
        ],
        "菲島福木\/福木": [
            [
                121.301269,
                25.009239
            ],
            [
                121.301324,
                25.009214
            ],
            [
                121.301381,
                25.009157
            ],
            [
                121.301049,
                25.008943
            ],
            [
                121.300942,
                25.009096
            ]
        ],
        "垂榕": [
            [
                121.301378,
                25.009927
            ],
            [
                121.301354,
                25.009978
            ],
            [
                121.301337,
                25.009998
            ],
            [
                121.301333,
                25.010019
            ],
            [
                121.301319,
                25.010028
            ],
            [
                121.30103,
                25.009886
            ],
            [
                121.301016,
                25.009874
            ],
            [
                121.301005,
                25.009862
            ],
            [
                121.300932,
                25.009787
            ],
            [
                121.30091,
                25.009764
            ],
            [
                121.300887,
                25.00974
            ]
        ],
        "九芎": [
            [
                121.301343,
                25.009077
            ],
            [
                121.301332,
                25.00907
            ],
            [
                121.301197,
                25.009229
            ]
        ],
        "光蠟樹\/白蠟樹\/白雞油": [
            [
                121.301297,
                25.010061
            ],
            [
                121.301268,
                25.010041
            ]
        ],
        "茄苳\/重陽木": [
            [
                121.301225,
                25.010039
            ]
        ],
        "海檬果": [
            [
                121.301233,
                25.01002
            ]
        ],
        "三角椰子": [
            [
                121.301263,
                25.009047
            ],
            [
                121.300514,
                25.009453
            ],
            [
                121.300477,
                25.009432
            ],
            [
                121.30005,
                25.009162
            ],
            [
                121.300066,
                25.009179
            ],
            [
                121.300426,
                25.009407
            ],
            [
                121.300088,
                25.009191
            ],
            [
                121.300371,
                25.009355
            ],
            [
                121.300113,
                25.009202
            ],
            [
                121.300346,
                25.009329
            ],
            [
                121.300142,
                25.009226
            ],
            [
                121.300316,
                25.009314
            ],
            [
                121.300168,
                25.009239
            ],
            [
                121.300292,
                25.009305
            ],
            [
                121.300189,
                25.009248
            ],
            [
                121.300261,
                25.009301
            ],
            [
                121.300218,
                25.009267
            ],
            [
                121.300244,
                25.009293
            ],
            [
                121.300228,
                25.009275
            ],
            [
                121.300229,
                25.009287
            ]
        ],
        "柳丁": [
            [
                121.301208,
                25.009027
            ]
        ],
        "臺灣欒樹\/台灣欒樹": [
            [
                121.301923,
                25.008887
            ],
            [
                121.30194,
                25.008852
            ],
            [
                121.301959,
                25.008812
            ],
            [
                121.301973,
                25.008794
            ],
            [
                121.301988,
                25.00877
            ],
            [
                121.301649,
                25.008492
            ],
            [
                121.301671,
                25.008502
            ],
            [
                121.301708,
                25.008875
            ],
            [
                121.301666,
                25.008856
            ],
            [
                121.30164,
                25.008846
            ],
            [
                121.301156,
                25.008698
            ],
            [
                121.300385,
                25.008477
            ],
            [
                121.300434,
                25.008446
            ],
            [
                121.300489,
                25.008426
            ],
            [
                121.299782,
                25.009027
            ],
            [
                121.300556,
                25.009379
            ],
            [
                121.300502,
                25.009365
            ],
            [
                121.300466,
                25.00934
            ],
            [
                121.300026,
                25.009149
            ],
            [
                121.300822,
                25.008711
            ],
            [
                121.300886,
                25.008737
            ]
        ],
        "小葉欖仁": [
            [
                121.301102,
                25.009018
            ],
            [
                121.300535,
                25.009293
            ]
        ],
        "水黃皮": [
            [
                121.301998,
                25.008733
            ],
            [
                121.301985,
                25.008707
            ],
            [
                121.301925,
                25.008607
            ],
            [
                121.301877,
                25.008588
            ],
            [
                121.301828,
                25.008569
            ],
            [
                121.301783,
                25.00855
            ],
            [
                121.301693,
                25.008506
            ],
            [
                121.301734,
                25.008531
            ]
        ],
        "小葉桑": [
            [
                121.300848,
                25.009652
            ],
            [
                121.301461,
                25.008438
            ],
            [
                121.301094,
                25.008601
            ],
            [
                121.299882,
                25.009096
            ],
            [
                121.299939,
                25.009122
            ]
        ],
        "福爾摩沙櫻花\/山白櫻\/白花山櫻花": [
            [
                121.301193,
                25.009861
            ]
        ],
        "山櫻花": [
            [
                121.301203,
                25.009839
            ],
            [
                121.301208,
                25.009801
            ],
            [
                121.301239,
                25.009728
            ],
            [
                121.301287,
                25.00962
            ]
        ],
        "竹柏": [
            [
                121.301202,
                25.009827
            ]
        ],
        "龍柏": [
            [
                121.301373,
                25.008589
            ],
            [
                121.301357,
                25.008617
            ],
            [
                121.301341,
                25.008642
            ],
            [
                121.301332,
                25.008668
            ],
            [
                121.301124,
                25.009184
            ],
            [
                121.301164,
                25.009209
            ]
        ],
        "毛女貞\/小蠟": [
            [
                121.301094,
                25.008984
            ],
            [
                121.30119,
                25.009218
            ],
            [
                121.301242,
                25.009246
            ]
        ],
        "馬拉巴栗": [
            [
                121.301072,
                25.008974
            ],
            [
                121.301042,
                25.008961
            ]
        ],
        "凹葉柃木": [
            [
                121.301031,
                25.008941
            ],
            [
                121.301054,
                25.008946
            ],
            [
                121.301078,
                25.008955
            ],
            [
                121.301085,
                25.00896
            ],
            [
                121.301112,
                25.008971
            ],
            [
                121.301122,
                25.008977
            ]
        ],
        "印度塔樹\/長葉暗羅": [
            [
                121.301003,
                25.008524
            ],
            [
                121.300987,
                25.008557
            ],
            [
                121.300976,
                25.00858
            ],
            [
                121.301132,
                25.00829
            ],
            [
                121.301118,
                25.008323
            ],
            [
                121.3011,
                25.00835
            ],
            [
                121.301082,
                25.008381
            ],
            [
                121.301059,
                25.008418
            ],
            [
                121.30104,
                25.008455
            ],
            [
                121.301024,
                25.008477
            ],
            [
                121.30101,
                25.008506
            ]
        ],
        "澳洲鴨腳木": [
            [
                121.301,
                25.009019
            ]
        ],
        "蘭嶼羅漢松": [
            [
                121.301532,
                25.009459
            ],
            [
                121.301523,
                25.009457
            ],
            [
                121.300979,
                25.00911
            ],
            [
                121.301516,
                25.009452
            ],
            [
                121.301507,
                25.00945
            ],
            [
                121.3015,
                25.009449
            ],
            [
                121.301489,
                25.009445
            ],
            [
                121.301477,
                25.009441
            ],
            [
                121.301471,
                25.00944
            ],
            [
                121.301461,
                25.009439
            ]
        ],
        "桂花": [
            [
                121.301,
                25.009109
            ],
            [
                121.301218,
                25.00923
            ]
        ],
        "金露花\/金露華": [
            [
                121.301162,
                25.009204
            ],
            [
                121.30117,
                25.009212
            ],
            [
                121.301172,
                25.00921
            ],
            [
                121.301175,
                25.00921
            ],
            [
                121.301206,
                25.009227
            ],
            [
                121.301228,
                25.009234
            ],
            [
                121.301226,
                25.009239
            ]
        ],
        "象腳王蘭": [
            [
                121.30122,
                25.009234
            ]
        ],
        "七里香\/月橘": [
            [
                121.301243,
                25.009246
            ]
        ],
        "楊桃": [
            [
                121.300451,
                25.00932
            ]
        ],
        "構樹": [
            [
                121.299856,
                25.009083
            ],
            [
                121.299899,
                25.009103
            ],
            [
                121.299904,
                25.009105
            ],
            [
                121.299949,
                25.009127
            ]
        ],
        "苦楝": [
            [
                121.299923,
                25.009115
            ]
        ],
        "白玉蘭\/玉蘭花": [
            [
                121.300776,
                25.008754
            ]
        ]
    }
}