{
    "info": {
        "代碼": "054643",
        "學校名稱": "縣立圳頭國小",
        "公\/私立": "公立",
        "縣市名稱": "[05]苗栗縣",
        "地址": "[357]苗栗縣通霄鎮圳頭里60號",
        "電話": "(037)754434",
        "網址": "http:\/\/www.toes.mlc.edu.tw"
    },
    "tree": {
        "緬梔\/雞蛋花": [
            [
                120.707643,
                24.483783
            ],
            [
                120.70769,
                24.483784
            ],
            [
                120.707839,
                24.483735
            ]
        ],
        "藍花楹": [
            [
                120.707702,
                24.483791
            ]
        ],
        "臺灣二葉松\/台灣二葉松": [
            [
                120.707634,
                24.483737
            ]
        ],
        "無患子": [
            [
                120.708787,
                24.483628
            ]
        ],
        "番石榴\/芭樂": [
            [
                120.707683,
                24.483741
            ]
        ],
        "榕樹\/正榕": [
            [
                120.708866,
                24.483794
            ],
            [
                120.708746,
                24.483557
            ],
            [
                120.708412,
                24.483958
            ],
            [
                120.708331,
                24.483979
            ],
            [
                120.708769,
                24.483823
            ],
            [
                120.708687,
                24.48385
            ]
        ],
        "龍柏": [
            [
                120.708309,
                24.483949
            ],
            [
                120.708358,
                24.483937
            ],
            [
                120.708737,
                24.483545
            ],
            [
                120.708388,
                24.483926
            ],
            [
                120.707654,
                24.484111
            ],
            [
                120.708414,
                24.483917
            ],
            [
                120.708426,
                24.483917
            ],
            [
                120.708437,
                24.483915
            ],
            [
                120.708447,
                24.483914
            ],
            [
                120.708457,
                24.483911
            ],
            [
                120.707715,
                24.484117
            ],
            [
                120.708447,
                24.483946
            ],
            [
                120.708622,
                24.483567
            ],
            [
                120.707764,
                24.484107
            ],
            [
                120.707823,
                24.484086
            ],
            [
                120.708602,
                24.48357
            ],
            [
                120.708602,
                24.483583
            ],
            [
                120.708577,
                24.483583
            ],
            [
                120.708586,
                24.483866
            ],
            [
                120.708549,
                24.483589
            ],
            [
                120.708599,
                24.483862
            ],
            [
                120.70852,
                24.483605
            ],
            [
                120.708618,
                24.483853
            ],
            [
                120.708481,
                24.483616
            ],
            [
                120.708635,
                24.483848
            ],
            [
                120.70788,
                24.484078
            ],
            [
                120.708459,
                24.48362
            ],
            [
                120.708667,
                24.483838
            ],
            [
                120.708443,
                24.483628
            ],
            [
                120.708696,
                24.483829
            ],
            [
                120.707946,
                24.484063
            ],
            [
                120.708425,
                24.483634
            ],
            [
                120.708724,
                24.483823
            ],
            [
                120.708403,
                24.483641
            ],
            [
                120.708737,
                24.48382
            ],
            [
                120.707997,
                24.484049
            ],
            [
                120.70837,
                24.483652
            ],
            [
                120.708755,
                24.483813
            ],
            [
                120.708778,
                24.483804
            ],
            [
                120.708345,
                24.483663
            ],
            [
                120.708317,
                24.48367
            ],
            [
                120.708791,
                24.483817
            ],
            [
                120.708034,
                24.484048
            ],
            [
                120.708663,
                24.483856
            ],
            [
                120.708065,
                24.484034
            ],
            [
                120.70808,
                24.484031
            ],
            [
                120.708115,
                24.484021
            ]
        ],
        "阿勃勒\/波斯皂莢": [
            [
                120.707695,
                24.48374
            ],
            [
                120.708212,
                24.483715
            ],
            [
                120.708192,
                24.483723
            ],
            [
                120.708051,
                24.483744
            ],
            [
                120.708037,
                24.483737
            ]
        ],
        "酒瓶椰子": [
            [
                120.708329,
                24.483934
            ],
            [
                120.708376,
                24.483937
            ],
            [
                120.708402,
                24.483922
            ],
            [
                120.708652,
                24.483563
            ],
            [
                120.708643,
                24.483568
            ],
            [
                120.70863,
                24.483575
            ],
            [
                120.708616,
                24.483582
            ],
            [
                120.708654,
                24.483842
            ],
            [
                120.708681,
                24.483836
            ],
            [
                120.70871,
                24.483827
            ]
        ],
        "楓香": [
            [
                120.708894,
                24.483778
            ],
            [
                120.708895,
                24.483787
            ],
            [
                120.708901,
                24.483796
            ]
        ],
        "小葉欖仁": [
            [
                120.708704,
                24.483557
            ]
        ],
        "大王椰子": [
            [
                120.70881,
                24.483807
            ],
            [
                120.708783,
                24.483815
            ],
            [
                120.708757,
                24.483824
            ],
            [
                120.70873,
                24.483832
            ],
            [
                120.708703,
                24.483841
            ],
            [
                120.708677,
                24.48385
            ],
            [
                120.708651,
                24.483858
            ],
            [
                120.708546,
                24.483913
            ],
            [
                120.708516,
                24.483925
            ],
            [
                120.708485,
                24.48394
            ],
            [
                120.708444,
                24.483966
            ],
            [
                120.708409,
                24.483975
            ],
            [
                120.708379,
                24.483983
            ]
        ],
        "大花紫薇": [
            [
                120.708142,
                24.483727
            ],
            [
                120.708285,
                24.483677
            ]
        ],
        "榔榆\/紅雞油": [
            [
                120.70812,
                24.483739
            ]
        ],
        "朴樹\/沙朴": [
            [
                120.708606,
                24.483584
            ]
        ],
        "螺旋葉變葉木\/紅鑽變葉木": [
            [
                120.707787,
                24.4841
            ],
            [
                120.707845,
                24.484085
            ],
            [
                120.707975,
                24.484055
            ],
            [
                120.708021,
                24.484052
            ],
            [
                120.708098,
                24.484024
            ]
        ],
        "斑葉榕\/黃斑榕": [
            [
                120.70791,
                24.484072
            ]
        ],
        "羊蹄甲": [
            [
                120.7081,
                24.483744
            ],
            [
                120.708074,
                24.483748
            ]
        ],
        "細葉變葉木": [
            [
                120.708822,
                24.483804
            ]
        ],
        "竹柏": [
            [
                120.708057,
                24.484034
            ]
        ]
    }
}