{
    "info": {
        "代碼": "084750",
        "學校名稱": "縣立康壽國小",
        "公\/私立": "公立",
        "縣市名稱": "[08]南投縣",
        "地址": "[540]南投縣南投市南陽路269號",
        "電話": "(049)2243457",
        "網址": "http:\/\/www.kses.ntct.edu.tw"
    },
    "tree": {
        "臺灣五葉松\/台灣五葉松": [
            [
                120.686768,
                23.913334
            ]
        ],
        "樟樹": [
            [
                120.686971,
                23.913296
            ],
            [
                120.685764,
                23.912999
            ],
            [
                120.685041,
                23.912671
            ],
            [
                120.686275,
                23.913529
            ],
            [
                120.686152,
                23.913519
            ],
            [
                120.685198,
                23.912125
            ],
            [
                120.685256,
                23.912129
            ]
        ],
        "七里香\/月橘": [
            [
                120.6862,
                23.913243
            ],
            [
                120.686992,
                23.913312
            ],
            [
                120.686151,
                23.913089
            ],
            [
                120.68703,
                23.913372
            ],
            [
                120.686783,
                23.913283
            ],
            [
                120.686781,
                23.913253
            ],
            [
                120.686782,
                23.913225
            ],
            [
                120.686787,
                23.913183
            ],
            [
                120.686789,
                23.913146
            ],
            [
                120.686792,
                23.913026
            ],
            [
                120.686786,
                23.913072
            ],
            [
                120.686789,
                23.913114
            ],
            [
                120.685839,
                23.912892
            ],
            [
                120.685922,
                23.912907
            ],
            [
                120.686606,
                23.913485
            ],
            [
                120.685516,
                23.913365
            ],
            [
                120.685512,
                23.913483
            ],
            [
                120.685356,
                23.913382
            ],
            [
                120.686551,
                23.913363
            ],
            [
                120.686579,
                23.912749
            ]
        ],
        "竹柏": [
            [
                120.686159,
                23.913271
            ],
            [
                120.686139,
                23.913269
            ],
            [
                120.686119,
                23.913271
            ],
            [
                120.686093,
                23.91327
            ],
            [
                120.686066,
                23.91327
            ],
            [
                120.686224,
                23.913024
            ],
            [
                120.686225,
                23.913006
            ],
            [
                120.686224,
                23.912993
            ],
            [
                120.686225,
                23.912981
            ],
            [
                120.686224,
                23.91296
            ],
            [
                120.684771,
                23.912821
            ],
            [
                120.685246,
                23.912786
            ],
            [
                120.685119,
                23.912781
            ],
            [
                120.685826,
                23.913002
            ],
            [
                120.685826,
                23.913017
            ],
            [
                120.685827,
                23.91303
            ],
            [
                120.685826,
                23.913043
            ],
            [
                120.685825,
                23.913057
            ],
            [
                120.685824,
                23.913078
            ],
            [
                120.685823,
                23.913159
            ],
            [
                120.685821,
                23.913177
            ],
            [
                120.685823,
                23.913194
            ],
            [
                120.685002,
                23.913266
            ],
            [
                120.685821,
                23.913211
            ],
            [
                120.685004,
                23.913293
            ],
            [
                120.68582,
                23.913225
            ],
            [
                120.685818,
                23.91327
            ],
            [
                120.685841,
                23.913272
            ],
            [
                120.685863,
                23.913271
            ],
            [
                120.685883,
                23.913275
            ],
            [
                120.685079,
                23.913276
            ],
            [
                120.685078,
                23.913301
            ],
            [
                120.685079,
                23.913322
            ],
            [
                120.685055,
                23.912883
            ],
            [
                120.68512,
                23.912601
            ],
            [
                120.685009,
                23.912566
            ]
        ],
        "龍眼\/龍眼樹": [
            [
                120.687004,
                23.913336
            ]
        ],
        "洋紅風鈴木\/粉風鈴木": [
            [
                120.686166,
                23.912767
            ],
            [
                120.686138,
                23.912821
            ],
            [
                120.686113,
                23.912866
            ],
            [
                120.68608,
                23.91288
            ],
            [
                120.686003,
                23.912861
            ],
            [
                120.685842,
                23.912865
            ],
            [
                120.685915,
                23.912894
            ],
            [
                120.68584,
                23.912884
            ]
        ],
        "苦楝": [
            [
                120.686192,
                23.912783
            ],
            [
                120.684567,
                23.913086
            ],
            [
                120.684664,
                23.913413
            ],
            [
                120.684961,
                23.912425
            ],
            [
                120.68532,
                23.913341
            ],
            [
                120.685257,
                23.912132
            ],
            [
                120.685344,
                23.913161
            ],
            [
                120.685333,
                23.913145
            ],
            [
                120.686255,
                23.91245
            ]
        ],
        "臺灣欒樹\/台灣欒樹": [
            [
                120.684453,
                23.913367
            ],
            [
                120.684433,
                23.913356
            ],
            [
                120.684439,
                23.913331
            ],
            [
                120.684445,
                23.913296
            ],
            [
                120.684465,
                23.91322
            ],
            [
                120.68445,
                23.913269
            ],
            [
                120.684469,
                23.913199
            ],
            [
                120.684477,
                23.91318
            ],
            [
                120.684483,
                23.913159
            ],
            [
                120.684489,
                23.913137
            ],
            [
                120.684506,
                23.9131
            ],
            [
                120.684516,
                23.91306
            ],
            [
                120.684523,
                23.91304
            ],
            [
                120.684548,
                23.91301
            ],
            [
                120.684565,
                23.912974
            ],
            [
                120.684583,
                23.912933
            ],
            [
                120.684596,
                23.912911
            ],
            [
                120.685081,
                23.912756
            ],
            [
                120.685159,
                23.912761
            ]
        ],
        "榕樹\/正榕": [
            [
                120.686161,
                23.913205
            ],
            [
                120.686163,
                23.913091
            ],
            [
                120.685756,
                23.912806
            ],
            [
                120.685489,
                23.912745
            ],
            [
                120.685772,
                23.912965
            ],
            [
                120.685851,
                23.913262
            ]
        ],
        "龍柏": [
            [
                120.687014,
                23.913328
            ]
        ],
        "桂花": [
            [
                120.687027,
                23.913363
            ],
            [
                120.686764,
                23.913071
            ]
        ],
        "山櫻花": [
            [
                120.686149,
                23.912882
            ],
            [
                120.685792,
                23.913
            ],
            [
                120.686523,
                23.912772
            ],
            [
                120.686544,
                23.912774
            ],
            [
                120.686567,
                23.912777
            ]
        ],
        "楓香": [
            [
                120.685977,
                23.912855
            ],
            [
                120.685941,
                23.912853
            ],
            [
                120.685806,
                23.912824
            ],
            [
                120.68584,
                23.912834
            ],
            [
                120.685885,
                23.912842
            ],
            [
                120.685913,
                23.912847
            ],
            [
                120.68571,
                23.912823
            ],
            [
                120.685681,
                23.912819
            ],
            [
                120.685651,
                23.912813
            ],
            [
                120.685614,
                23.912809
            ],
            [
                120.686495,
                23.912701
            ],
            [
                120.686452,
                23.91277
            ]
        ],
        "流蘇\/流疏": [
            [
                120.686236,
                23.913047
            ],
            [
                120.68654,
                23.913517
            ]
        ],
        "紅刺露兜樹": [
            [
                120.68615,
                23.912939
            ],
            [
                120.686055,
                23.912997
            ],
            [
                120.68654,
                23.912734
            ],
            [
                120.686573,
                23.912862
            ]
        ],
        "青剛櫟": [
            [
                120.68549,
                23.912799
            ],
            [
                120.685531,
                23.912801
            ],
            [
                120.685568,
                23.912806
            ],
            [
                120.685484,
                23.912775
            ],
            [
                120.685458,
                23.912802
            ],
            [
                120.685446,
                23.912774
            ]
        ],
        "麵包樹": [
            [
                120.68571,
                23.912799
            ],
            [
                120.685645,
                23.912774
            ],
            [
                120.684961,
                23.912568
            ],
            [
                120.685323,
                23.91268
            ],
            [
                120.685254,
                23.912669
            ],
            [
                120.685213,
                23.912667
            ],
            [
                120.685127,
                23.912644
            ]
        ],
        "黃椰子\/散尾葵": [
            [
                120.684571,
                23.913082
            ],
            [
                120.684907,
                23.913088
            ]
        ],
        "蘭嶼羅漢松": [
            [
                120.686684,
                23.913369
            ]
        ],
        "黃褥花\/巴佩道櫻桃\/大果黃褥花": [
            [
                120.68602,
                23.913006
            ],
            [
                120.685735,
                23.912896
            ],
            [
                120.6866,
                23.913435
            ],
            [
                120.68654,
                23.913482
            ],
            [
                120.684932,
                23.912542
            ],
            [
                120.685582,
                23.912885
            ],
            [
                120.686598,
                23.912814
            ],
            [
                120.686634,
                23.912972
            ]
        ],
        "欖仁樹": [
            [
                120.685437,
                23.912802
            ],
            [
                120.68541,
                23.912798
            ],
            [
                120.686564,
                23.91349
            ],
            [
                120.685194,
                23.91276
            ],
            [
                120.685234,
                23.912769
            ],
            [
                120.685262,
                23.912772
            ],
            [
                120.685287,
                23.912772
            ],
            [
                120.685315,
                23.912777
            ],
            [
                120.685332,
                23.912782
            ],
            [
                120.685348,
                23.912781
            ],
            [
                120.685376,
                23.912777
            ],
            [
                120.685411,
                23.912775
            ],
            [
                120.686084,
                23.913511
            ],
            [
                120.685445,
                23.912862
            ]
        ],
        "旅人蕉": [
            [
                120.686692,
                23.913511
            ],
            [
                120.686694,
                23.913518
            ],
            [
                120.686689,
                23.913523
            ],
            [
                120.686687,
                23.913518
            ],
            [
                120.686685,
                23.913524
            ],
            [
                120.68664,
                23.913505
            ],
            [
                120.686637,
                23.913507
            ],
            [
                120.686642,
                23.913518
            ],
            [
                120.686636,
                23.913523
            ],
            [
                120.686686,
                23.913522
            ],
            [
                120.686692,
                23.91352
            ],
            [
                120.686634,
                23.913519
            ]
        ],
        "阿勃勒\/波斯皂莢": [
            [
                120.684712,
                23.912813
            ],
            [
                120.684741,
                23.912814
            ],
            [
                120.686752,
                23.912953
            ],
            [
                120.68613,
                23.912881
            ],
            [
                120.686731,
                23.912934
            ],
            [
                120.686713,
                23.912921
            ],
            [
                120.68667,
                23.91283
            ],
            [
                120.686689,
                23.912891
            ],
            [
                120.686672,
                23.91288
            ],
            [
                120.686681,
                23.912868
            ]
        ],
        "水黃皮": [
            [
                120.685375,
                23.912798
            ],
            [
                120.68535,
                23.912796
            ],
            [
                120.685119,
                23.91276
            ],
            [
                120.68519,
                23.912844
            ],
            [
                120.685281,
                23.912851
            ],
            [
                120.685391,
                23.912861
            ],
            [
                120.68544,
                23.912857
            ],
            [
                120.685528,
                23.912853
            ],
            [
                120.685579,
                23.912864
            ],
            [
                120.685574,
                23.912904
            ],
            [
                120.685615,
                23.912872
            ],
            [
                120.685646,
                23.912874
            ],
            [
                120.685675,
                23.912878
            ],
            [
                120.685713,
                23.912887
            ]
        ],
        "波羅蜜": [
            [
                120.685316,
                23.912798
            ],
            [
                120.685289,
                23.912787
            ],
            [
                120.685194,
                23.912783
            ],
            [
                120.68516,
                23.912782
            ],
            [
                120.685087,
                23.912779
            ]
        ],
        "金露花\/金露華": [
            [
                120.685866,
                23.9129
            ],
            [
                120.685895,
                23.912905
            ],
            [
                120.685928,
                23.912918
            ],
            [
                120.685759,
                23.912896
            ],
            [
                120.685543,
                23.913486
            ],
            [
                120.685433,
                23.913426
            ],
            [
                120.686763,
                23.913102
            ]
        ],
        "大花紫薇": [
            [
                120.684822,
                23.91343
            ],
            [
                120.685091,
                23.912731
            ]
        ],
        "榔榆\/紅雞油": [
            [
                120.685029,
                23.912799
            ],
            [
                120.684991,
                23.912768
            ],
            [
                120.684997,
                23.912734
            ],
            [
                120.684958,
                23.912738
            ],
            [
                120.684995,
                23.912698
            ],
            [
                120.685037,
                23.912706
            ],
            [
                120.685001,
                23.912667
            ],
            [
                120.686452,
                23.912598
            ],
            [
                120.686418,
                23.912684
            ],
            [
                120.686401,
                23.912725
            ],
            [
                120.686382,
                23.912772
            ]
        ],
        "小葉欖仁": [
            [
                120.684994,
                23.912796
            ],
            [
                120.684958,
                23.912798
            ],
            [
                120.686629,
                23.913522
            ],
            [
                120.686464,
                23.91353
            ],
            [
                120.685085,
                23.912881
            ],
            [
                120.686027,
                23.913505
            ],
            [
                120.685969,
                23.91351
            ],
            [
                120.685857,
                23.91351
            ],
            [
                120.68574,
                23.913507
            ],
            [
                120.685436,
                23.912856
            ]
        ],
        "陰香\/印尼肉桂\/假肉桂": [
            [
                120.685077,
                23.913126
            ],
            [
                120.685075,
                23.913154
            ],
            [
                120.685074,
                23.91318
            ],
            [
                120.685072,
                23.913207
            ],
            [
                120.685044,
                23.913129
            ],
            [
                120.685016,
                23.913131
            ],
            [
                120.685016,
                23.913157
            ],
            [
                120.685015,
                23.913181
            ],
            [
                120.685015,
                23.913204
            ],
            [
                120.685013,
                23.913221
            ],
            [
                120.686325,
                23.913537
            ],
            [
                120.684894,
                23.912514
            ],
            [
                120.685938,
                23.912347
            ],
            [
                120.686532,
                23.913359
            ]
        ],
        "大王椰子": [
            [
                120.686643,
                23.913515
            ],
            [
                120.686544,
                23.913443
            ],
            [
                120.686117,
                23.9124
            ],
            [
                120.686166,
                23.912432
            ],
            [
                120.686216,
                23.912452
            ],
            [
                120.68628,
                23.912476
            ]
        ],
        "九芎": [
            [
                120.684965,
                23.912695
            ]
        ],
        "光蠟樹\/白蠟樹\/白雞油": [
            [
                120.685045,
                23.913157
            ],
            [
                120.685044,
                23.913183
            ],
            [
                120.685046,
                23.913211
            ]
        ],
        "芒果\/芒果樹": [
            [
                120.684928,
                23.91262
            ],
            [
                120.684906,
                23.912673
            ],
            [
                120.684884,
                23.912734
            ],
            [
                120.684856,
                23.912793
            ]
        ],
        "檳榔": [
            [
                120.686603,
                23.913532
            ],
            [
                120.686574,
                23.913534
            ]
        ],
        "穗花棋盤腳\/水茄苳": [
            [
                120.685112,
                23.912672
            ],
            [
                120.68512,
                23.912734
            ],
            [
                120.685213,
                23.912744
            ],
            [
                120.68525,
                23.91275
            ],
            [
                120.685124,
                23.912712
            ],
            [
                120.685164,
                23.91272
            ],
            [
                120.685211,
                23.912725
            ],
            [
                120.685246,
                23.912731
            ],
            [
                120.685266,
                23.912739
            ],
            [
                120.685178,
                23.912656
            ],
            [
                120.685163,
                23.912695
            ],
            [
                120.685203,
                23.912706
            ],
            [
                120.684949,
                23.912544
            ]
        ],
        "人心果": [
            [
                120.685005,
                23.913316
            ]
        ],
        "大葉桃花心木": [
            [
                120.686411,
                23.913534
            ]
        ],
        "構樹": [
            [
                120.685072,
                23.913307
            ],
            [
                120.685076,
                23.912957
            ],
            [
                120.685124,
                23.912712
            ]
        ],
        "茄苳\/重陽木": [
            [
                120.685405,
                23.912745
            ],
            [
                120.685175,
                23.912739
            ],
            [
                120.685324,
                23.912725
            ]
        ],
        "鳳凰木": [
            [
                120.685486,
                23.913417
            ],
            [
                120.685323,
                23.913311
            ],
            [
                120.685321,
                23.913285
            ],
            [
                120.685422,
                23.913153
            ],
            [
                120.685487,
                23.91315
            ],
            [
                120.685517,
                23.913157
            ],
            [
                120.685517,
                23.913193
            ],
            [
                120.686433,
                23.912649
            ]
        ],
        "檸檬": [
            [
                120.68509,
                23.912933
            ]
        ],
        "蘭嶼柿": [
            [
                120.685185,
                23.912883
            ]
        ],
        "桃樹\/桃子": [
            [
                120.685458,
                23.913481
            ]
        ],
        "馬拉巴栗": [
            [
                120.685405,
                23.913481
            ]
        ],
        "楊桃": [
            [
                120.685361,
                23.91349
            ]
        ],
        "血桐": [
            [
                120.685111,
                23.912676
            ]
        ],
        "琉球莢蒾": [
            [
                120.685405,
                23.913421
            ]
        ],
        "美人樹": [
            [
                120.68565,
                23.913509
            ],
            [
                120.685624,
                23.913519
            ],
            [
                120.685551,
                23.913511
            ],
            [
                120.685312,
                23.91348
            ]
        ],
        "草莓番石榴\/榕葉芭樂\/草莓芭樂": [
            [
                120.685443,
                23.913443
            ]
        ],
        "掌葉蘋婆": [
            [
                120.685598,
                23.913508
            ]
        ],
        "森氏紅淡比": [
            [
                120.684931,
                23.91247
            ],
            [
                120.68506,
                23.912304
            ],
            [
                120.685079,
                23.912269
            ],
            [
                120.685101,
                23.912246
            ],
            [
                120.68513,
                23.912211
            ],
            [
                120.685148,
                23.912181
            ],
            [
                120.685163,
                23.912152
            ],
            [
                120.686093,
                23.912395
            ]
        ],
        "菲律賓饅頭果": [
            [
                120.68499,
                23.912386
            ]
        ],
        "緬梔\/雞蛋花": [
            [
                120.686592,
                23.913351
            ],
            [
                120.686567,
                23.913328
            ]
        ],
        "垂榕": [
            [
                120.686035,
                23.912385
            ]
        ],
        "螺旋葉變葉木\/紅鑽變葉木": [
            [
                120.686535,
                23.913302
            ],
            [
                120.686533,
                23.9133
            ],
            [
                120.686533,
                23.913299
            ],
            [
                120.686533,
                23.913299
            ]
        ],
        "小葉桑": [
            [
                120.686267,
                23.912795
            ]
        ],
        "風鈴木": [
            [
                120.686335,
                23.912799
            ]
        ],
        "白玉蘭\/玉蘭花": [
            [
                120.686362,
                23.912805
            ],
            [
                120.686447,
                23.912791
            ],
            [
                120.686633,
                23.912931
            ]
        ],
        "梅花": [
            [
                120.686422,
                23.912769
            ],
            [
                120.686436,
                23.912733
            ],
            [
                120.686488,
                23.912619
            ],
            [
                120.686519,
                23.912655
            ],
            [
                120.686554,
                23.912699
            ],
            [
                120.686721,
                23.913468
            ]
        ],
        "海檬果": [
            [
                120.686558,
                23.913027
            ]
        ],
        "蘭嶼肉桂": [
            [
                120.686473,
                23.912731
            ]
        ],
        "小葉黃褥花\/小李櫻桃\/珍珠櫻桃": [
            [
                120.686391,
                23.912804
            ],
            [
                120.686406,
                23.912805
            ]
        ],
        "貝殼杉": [
            [
                120.686541,
                23.912663
            ],
            [
                120.68657,
                23.912699
            ],
            [
                120.686596,
                23.912727
            ],
            [
                120.686616,
                23.912761
            ]
        ],
        "菩提樹": [
            [
                120.686634,
                23.912846
            ]
        ]
    }
}