{
    "info": {
        "代碼": "173610",
        "學校名稱": "市立東光國小",
        "公\/私立": "公立",
        "縣市名稱": "[17]基隆市",
        "地址": "[201]基隆市信義區東信路236巷16號",
        "電話": "(02)24650329",
        "網址": "http:\/\/www.dgps.kl.edu.tw"
    },
    "tree": {
        "山櫻花": [
            [
                121.763178,
                25.129546
            ],
            [
                121.763152,
                25.129563
            ]
        ],
        "山黃梔\/梔子花": [
            [
                121.762816,
                25.12898
            ]
        ],
        "土肉桂": [
            [
                121.762889,
                25.129349
            ],
            [
                121.762882,
                25.129329
            ]
        ],
        "陰香\/印尼肉桂\/假肉桂": [
            [
                121.762883,
                25.129311
            ],
            [
                121.762877,
                25.129297
            ],
            [
                121.762876,
                25.129279
            ],
            [
                121.762875,
                25.129262
            ],
            [
                121.762871,
                25.12925
            ],
            [
                121.762865,
                25.129241
            ]
        ],
        "小葉桑": [
            [
                121.762864,
                25.12923
            ],
            [
                121.763008,
                25.129812
            ]
        ],
        "七里香\/月橘": [
            [
                121.763069,
                25.129738
            ],
            [
                121.763033,
                25.129772
            ],
            [
                121.762984,
                25.129819
            ]
        ],
        "茄苳\/重陽木": [
            [
                121.763043,
                25.129772
            ]
        ],
        "菲島福木\/福木": [
            [
                121.762903,
                25.129689
            ],
            [
                121.762893,
                25.129682
            ]
        ]
    }
}