{
    "type": "FeatureCollection",
    "features": [
        {
            "type": "Feature",
            "properties": {
                "code": "064636",
                "count": 1
            },
            "geometry": {
                "type": "Point",
                "coordinates": [
                    120.835779905,
                    24.2527563655
                ]
            }
        },
        {
            "type": "Feature",
            "properties": {
                "code": "413605",
                "count": 1
            },
            "geometry": {
                "type": "Point",
                "coordinates": [
                    121.50286569,
                    25.0906875265
                ]
            }
        },
        {
            "type": "Feature",
            "properties": {
                "code": "413F02",
                "count": 1
            },
            "geometry": {
                "type": "Point",
                "coordinates": [
                    121.53105762999999,
                    25.1054353555
                ]
            }
        },
        {
            "type": "Feature",
            "properties": {
                "code": "413F01",
                "count": 1
            },
            "geometry": {
                "type": "Point",
                "coordinates": [
                    121.53105762999999,
                    25.1054353555
                ]
            }
        },
        {
            "type": "Feature",
            "properties": {
                "code": "064602",
                "count": 1
            },
            "geometry": {
                "type": "Point",
                "coordinates": [
                    120.71196377000001,
                    24.249828957
                ]
            }
        },
        {
            "type": "Feature",
            "properties": {
                "code": "064730",
                "count": 1
            },
            "geometry": {
                "type": "Point",
                "coordinates": [
                    120.88115031,
                    24.163596775000002
                ]
            }
        },
        {
            "type": "Feature",
            "properties": {
                "code": "080401",
                "count": 1
            },
            "geometry": {
                "type": "Point",
                "coordinates": [
                    121.13353862,
                    24.021645155999998
                ]
            }
        },
        {
            "type": "Feature",
            "properties": {
                "code": "084672",
                "count": 1
            },
            "geometry": {
                "type": "Point",
                "coordinates": [
                    120.780756725,
                    23.7132636535
                ]
            }
        },
        {
            "type": "Feature",
            "properties": {
                "code": "054669",
                "count": 2
            },
            "geometry": {
                "type": "Point",
                "coordinates": [
                    121.00847996,
                    24.6292982535
                ]
            }
        },
        {
            "type": "Feature",
            "properties": {
                "code": "084622",
                "count": 1
            },
            "geometry": {
                "type": "Point",
                "coordinates": [
                    120.9262804,
                    23.942002263
                ]
            }
        }
    ]
}