{
    "type": "FeatureCollection",
    "features": [
        {
            "type": "Feature",
            "properties": {
                "code": "034731",
                "count": 3
            },
            "geometry": {
                "type": "Point",
                "coordinates": [
                    121.33091969,
                    24.832859662
                ]
            }
        },
        {
            "type": "Feature",
            "properties": {
                "code": "014805",
                "count": 1
            },
            "geometry": {
                "type": "Point",
                "coordinates": [
                    121.420204435,
                    25.1601398985
                ]
            }
        },
        {
            "type": "Feature",
            "properties": {
                "code": "034713",
                "count": 1
            },
            "geometry": {
                "type": "Point",
                "coordinates": [
                    121.058899785,
                    25.021289263
                ]
            }
        },
        {
            "type": "Feature",
            "properties": {
                "code": "034666",
                "count": 1
            },
            "geometry": {
                "type": "Point",
                "coordinates": [
                    121.22081844499999,
                    24.954417825
                ]
            }
        },
        {
            "type": "Feature",
            "properties": {
                "code": "124F01",
                "count": 3
            },
            "geometry": {
                "type": "Point",
                "coordinates": [
                    120.352777755,
                    22.692639486
                ]
            }
        },
        {
            "type": "Feature",
            "properties": {
                "code": "124536",
                "count": 1
            },
            "geometry": {
                "type": "Point",
                "coordinates": [
                    120.453560735,
                    22.921303389000002
                ]
            }
        },
        {
            "type": "Feature",
            "properties": {
                "code": "124302",
                "count": 1
            },
            "geometry": {
                "type": "Point",
                "coordinates": [
                    120.35289858499999,
                    22.6473021245
                ]
            }
        },
        {
            "type": "Feature",
            "properties": {
                "code": "124731",
                "count": 1
            },
            "geometry": {
                "type": "Point",
                "coordinates": [
                    120.720808415,
                    23.27602782
                ]
            }
        },
        {
            "type": "Feature",
            "properties": {
                "code": "064507",
                "count": 3
            },
            "geometry": {
                "type": "Point",
                "coordinates": [
                    120.6938717,
                    24.3078935495
                ]
            }
        },
        {
            "type": "Feature",
            "properties": {
                "code": "014786",
                "count": 1
            },
            "geometry": {
                "type": "Point",
                "coordinates": [
                    121.45656048000001,
                    25.0856605015
                ]
            }
        },
        {
            "type": "Feature",
            "properties": {
                "code": "014631",
                "count": 1
            },
            "geometry": {
                "type": "Point",
                "coordinates": [
                    121.437334195,
                    24.85386827
                ]
            }
        },
        {
            "type": "Feature",
            "properties": {
                "code": "034658",
                "count": 1
            },
            "geometry": {
                "type": "Point",
                "coordinates": [
                    121.31089765,
                    24.823592281
                ]
            }
        },
        {
            "type": "Feature",
            "properties": {
                "code": "014722",
                "count": 6
            },
            "geometry": {
                "type": "Point",
                "coordinates": [
                    121.46191003999999,
                    25.1367593345
                ]
            }
        },
        {
            "type": "Feature",
            "properties": {
                "code": "014642",
                "count": 1
            },
            "geometry": {
                "type": "Point",
                "coordinates": [
                    121.52153179999999,
                    24.999000784499998
                ]
            }
        },
        {
            "type": "Feature",
            "properties": {
                "code": "124620",
                "count": 9
            },
            "geometry": {
                "type": "Point",
                "coordinates": [
                    120.38349378000001,
                    22.615597213
                ]
            }
        },
        {
            "type": "Feature",
            "properties": {
                "code": "173516",
                "count": 1
            },
            "geometry": {
                "type": "Point",
                "coordinates": [
                    121.70568625499999,
                    25.1376226115
                ]
            }
        },
        {
            "type": "Feature",
            "properties": {
                "code": "173503",
                "count": 2
            },
            "geometry": {
                "type": "Point",
                "coordinates": [
                    121.76857559999999,
                    25.129477588500002
                ]
            }
        },
        {
            "type": "Feature",
            "properties": {
                "code": "183313",
                "count": 5
            },
            "geometry": {
                "type": "Point",
                "coordinates": [
                    121.001223635,
                    24.798230762
                ]
            }
        },
        {
            "type": "Feature",
            "properties": {
                "code": "183613",
                "count": 1
            },
            "geometry": {
                "type": "Point",
                "coordinates": [
                    120.99939080499999,
                    24.799993558
                ]
            }
        },
        {
            "type": "Feature",
            "properties": {
                "code": "173633",
                "count": 2
            },
            "geometry": {
                "type": "Point",
                "coordinates": [
                    121.721738665,
                    25.124593503
                ]
            }
        },
        {
            "type": "Feature",
            "properties": {
                "code": "173512",
                "count": 8
            },
            "geometry": {
                "type": "Point",
                "coordinates": [
                    121.721670865,
                    25.127163783999997
                ]
            }
        },
        {
            "type": "Feature",
            "properties": {
                "code": "064753",
                "count": 1
            },
            "geometry": {
                "type": "Point",
                "coordinates": [
                    120.7144609,
                    24.081776509
                ]
            }
        },
        {
            "type": "Feature",
            "properties": {
                "code": "124530",
                "count": 1
            },
            "geometry": {
                "type": "Point",
                "coordinates": [
                    120.54325277000001,
                    22.8939731635
                ]
            }
        },
        {
            "type": "Feature",
            "properties": {
                "code": "124524",
                "count": 1
            },
            "geometry": {
                "type": "Point",
                "coordinates": [
                    120.18128706499999,
                    22.905791973
                ]
            }
        },
        {
            "type": "Feature",
            "properties": {
                "code": "124548",
                "count": 1
            },
            "geometry": {
                "type": "Point",
                "coordinates": [
                    120.780760435,
                    23.1787966355
                ]
            }
        },
        {
            "type": "Feature",
            "properties": {
                "code": "183629",
                "count": 1
            },
            "geometry": {
                "type": "Point",
                "coordinates": [
                    120.98363301500001,
                    24.779551198
                ]
            }
        },
        {
            "type": "Feature",
            "properties": {
                "code": "553401",
                "count": 3
            },
            "geometry": {
                "type": "Point",
                "coordinates": [
                    120.326804815,
                    22.648719892000003
                ]
            }
        },
        {
            "type": "Feature",
            "properties": {
                "code": "183502",
                "count": 1
            },
            "geometry": {
                "type": "Point",
                "coordinates": [
                    120.978363805,
                    24.7932220055
                ]
            }
        },
        {
            "type": "Feature",
            "properties": {
                "code": "124541",
                "count": 3
            },
            "geometry": {
                "type": "Point",
                "coordinates": [
                    120.258980835,
                    22.728453273
                ]
            }
        },
        {
            "type": "Feature",
            "properties": {
                "code": "183625",
                "count": 1
            },
            "geometry": {
                "type": "Point",
                "coordinates": [
                    120.950010615,
                    24.797496045499997
                ]
            }
        },
        {
            "type": "Feature",
            "properties": {
                "code": "173638",
                "count": 10
            },
            "geometry": {
                "type": "Point",
                "coordinates": [
                    121.69373841,
                    25.156235001
                ]
            }
        },
        {
            "type": "Feature",
            "properties": {
                "code": "013F01",
                "count": 3
            },
            "geometry": {
                "type": "Point",
                "coordinates": [
                    121.35163092,
                    25.0976996725
                ]
            }
        },
        {
            "type": "Feature",
            "properties": {
                "code": "013335",
                "count": 4
            },
            "geometry": {
                "type": "Point",
                "coordinates": [
                    121.53288850999999,
                    24.975009614
                ]
            }
        },
        {
            "type": "Feature",
            "properties": {
                "code": "173307",
                "count": 2
            },
            "geometry": {
                "type": "Point",
                "coordinates": [
                    121.73790002,
                    25.1080620265
                ]
            }
        },
        {
            "type": "Feature",
            "properties": {
                "code": "034528",
                "count": 1
            },
            "geometry": {
                "type": "Point",
                "coordinates": [
                    121.148371755,
                    24.9039618185
                ]
            }
        },
        {
            "type": "Feature",
            "properties": {
                "code": "014789",
                "count": 1
            },
            "geometry": {
                "type": "Point",
                "coordinates": [
                    121.418528675,
                    25.021468864
                ]
            }
        },
        {
            "type": "Feature",
            "properties": {
                "code": "124639",
                "count": 1
            },
            "geometry": {
                "type": "Point",
                "coordinates": [
                    120.38018703,
                    22.7482872
                ]
            }
        },
        {
            "type": "Feature",
            "properties": {
                "code": "124758",
                "count": 1
            },
            "geometry": {
                "type": "Point",
                "coordinates": [
                    120.292033895,
                    22.798638464
                ]
            }
        },
        {
            "type": "Feature",
            "properties": {
                "code": "063F01",
                "count": 3
            },
            "geometry": {
                "type": "Point",
                "coordinates": [
                    120.71471112,
                    24.3131087135
                ]
            }
        },
        {
            "type": "Feature",
            "properties": {
                "code": "193F01",
                "count": 1
            },
            "geometry": {
                "type": "Point",
                "coordinates": [
                    120.627055095,
                    24.17937856
                ]
            }
        },
        {
            "type": "Feature",
            "properties": {
                "code": "124610",
                "count": 2
            },
            "geometry": {
                "type": "Point",
                "coordinates": [
                    120.350786745,
                    22.630533046
                ]
            }
        },
        {
            "type": "Feature",
            "properties": {
                "code": "034650",
                "count": 3
            },
            "geometry": {
                "type": "Point",
                "coordinates": [
                    121.264732175,
                    24.936656362500003
                ]
            }
        },
        {
            "type": "Feature",
            "properties": {
                "code": "124520",
                "count": 1
            },
            "geometry": {
                "type": "Point",
                "coordinates": [
                    120.363675675,
                    22.785699231000002
                ]
            }
        },
        {
            "type": "Feature",
            "properties": {
                "code": "014816",
                "count": 3
            },
            "geometry": {
                "type": "Point",
                "coordinates": [
                    121.37214326,
                    25.082638352
                ]
            }
        },
        {
            "type": "Feature",
            "properties": {
                "code": "064350",
                "count": 8
            },
            "geometry": {
                "type": "Point",
                "coordinates": [
                    120.521022235,
                    24.205606473000003
                ]
            }
        },
        {
            "type": "Feature",
            "properties": {
                "code": "033302",
                "count": 1
            },
            "geometry": {
                "type": "Point",
                "coordinates": [
                    121.222424555,
                    24.8484373655
                ]
            }
        },
        {
            "type": "Feature",
            "properties": {
                "code": "124526",
                "count": 6
            },
            "geometry": {
                "type": "Point",
                "coordinates": [
                    120.246016185,
                    22.776738579499998
                ]
            }
        },
        {
            "type": "Feature",
            "properties": {
                "code": "124534",
                "count": 1
            },
            "geometry": {
                "type": "Point",
                "coordinates": [
                    120.70285154999999,
                    23.109530612
                ]
            }
        },
        {
            "type": "Feature",
            "properties": {
                "code": "080305",
                "count": 2
            },
            "geometry": {
                "type": "Point",
                "coordinates": [
                    120.6950686,
                    23.950597214
                ]
            }
        },
        {
            "type": "Feature",
            "properties": {
                "code": "040308",
                "count": 1
            },
            "geometry": {
                "type": "Point",
                "coordinates": [
                    121.00303835,
                    24.835727168
                ]
            }
        },
        {
            "type": "Feature",
            "properties": {
                "code": "100301",
                "count": 4
            },
            "geometry": {
                "type": "Point",
                "coordinates": [
                    120.25185114,
                    23.4636129945
                ]
            }
        },
        {
            "type": "Feature",
            "properties": {
                "code": "150F01",
                "count": 7
            },
            "geometry": {
                "type": "Point",
                "coordinates": [
                    121.56569222,
                    24.4821371595
                ]
            }
        },
        {
            "type": "Feature",
            "properties": {
                "code": "710301",
                "count": 1
            },
            "geometry": {
                "type": "Point",
                "coordinates": [
                    118.313909755,
                    24.4355135925
                ]
            }
        },
        {
            "type": "Feature",
            "properties": {
                "code": "710401",
                "count": 7
            },
            "geometry": {
                "type": "Point",
                "coordinates": [
                    118.42554919,
                    24.443158914999998
                ]
            }
        },
        {
            "type": "Feature",
            "properties": {
                "code": "080F01",
                "count": 2
            },
            "geometry": {
                "type": "Point",
                "coordinates": [
                    120.67552462,
                    23.9227661075
                ]
            }
        },
        {
            "type": "Feature",
            "properties": {
                "code": "130417",
                "count": 3
            },
            "geometry": {
                "type": "Point",
                "coordinates": [
                    120.748695965,
                    21.9932264395
                ]
            }
        },
        {
            "type": "Feature",
            "properties": {
                "code": "180301",
                "count": 7
            },
            "geometry": {
                "type": "Point",
                "coordinates": [
                    121.016674935,
                    24.778154406
                ]
            }
        },
        {
            "type": "Feature",
            "properties": {
                "code": "050F01",
                "count": 1
            },
            "geometry": {
                "type": "Point",
                "coordinates": [
                    120.81632594000001,
                    24.557927695
                ]
            }
        },
        {
            "type": "Feature",
            "properties": {
                "code": "050404",
                "count": 1
            },
            "geometry": {
                "type": "Point",
                "coordinates": [
                    120.83311369500001,
                    24.555348116
                ]
            }
        },
        {
            "type": "Feature",
            "properties": {
                "code": "040F01",
                "count": 1
            },
            "geometry": {
                "type": "Point",
                "coordinates": [
                    121.002381095,
                    24.8344598045
                ]
            }
        },
        {
            "type": "Feature",
            "properties": {
                "code": "140F01",
                "count": 17
            },
            "geometry": {
                "type": "Point",
                "coordinates": [
                    121.12071126500001,
                    22.755546375
                ]
            }
        },
        {
            "type": "Feature",
            "properties": {
                "code": "140301",
                "count": 14
            },
            "geometry": {
                "type": "Point",
                "coordinates": [
                    121.07698972,
                    22.763608624
                ]
            }
        },
        {
            "type": "Feature",
            "properties": {
                "code": "020405",
                "count": 1
            },
            "geometry": {
                "type": "Point",
                "coordinates": [
                    121.84397182000001,
                    24.5927829175
                ]
            }
        },
        {
            "type": "Feature",
            "properties": {
                "code": "024526",
                "count": 9
            },
            "geometry": {
                "type": "Point",
                "coordinates": [
                    121.81956,
                    24.8598558345
                ]
            }
        },
        {
            "type": "Feature",
            "properties": {
                "code": "154669",
                "count": 1
            },
            "geometry": {
                "type": "Point",
                "coordinates": [
                    121.3483588,
                    23.4303530185
                ]
            }
        },
        {
            "type": "Feature",
            "properties": {
                "code": "154686",
                "count": 1
            },
            "geometry": {
                "type": "Point",
                "coordinates": [
                    121.606619475,
                    24.102909972
                ]
            }
        },
        {
            "type": "Feature",
            "properties": {
                "code": "084633",
                "count": 2
            },
            "geometry": {
                "type": "Point",
                "coordinates": [
                    120.742785725,
                    23.984099665
                ]
            }
        },
        {
            "type": "Feature",
            "properties": {
                "code": "144514",
                "count": 1
            },
            "geometry": {
                "type": "Point",
                "coordinates": [
                    120.906788385,
                    22.364666169000003
                ]
            }
        },
        {
            "type": "Feature",
            "properties": {
                "code": "104524",
                "count": 2
            },
            "geometry": {
                "type": "Point",
                "coordinates": [
                    120.591593135,
                    23.2939358415
                ]
            }
        },
        {
            "type": "Feature",
            "properties": {
                "code": "044522",
                "count": 1
            },
            "geometry": {
                "type": "Point",
                "coordinates": [
                    121.01796222499999,
                    24.8735552485
                ]
            }
        },
        {
            "type": "Feature",
            "properties": {
                "code": "134763",
                "count": 3
            },
            "geometry": {
                "type": "Point",
                "coordinates": [
                    120.75156602,
                    22.203847613
                ]
            }
        },
        {
            "type": "Feature",
            "properties": {
                "code": "044675",
                "count": 1
            },
            "geometry": {
                "type": "Point",
                "coordinates": [
                    121.112093555,
                    24.6039724045
                ]
            }
        },
        {
            "type": "Feature",
            "properties": {
                "code": "164646",
                "count": 5
            },
            "geometry": {
                "type": "Point",
                "coordinates": [
                    119.568405215,
                    23.5764312625
                ]
            }
        },
        {
            "type": "Feature",
            "properties": {
                "code": "104607",
                "count": 3
            },
            "geometry": {
                "type": "Point",
                "coordinates": [
                    120.172040165,
                    23.3816721145
                ]
            }
        },
        {
            "type": "Feature",
            "properties": {
                "code": "104503",
                "count": 2
            },
            "geometry": {
                "type": "Point",
                "coordinates": [
                    120.180501175,
                    23.3590130915
                ]
            }
        },
        {
            "type": "Feature",
            "properties": {
                "code": "104736",
                "count": 4
            },
            "geometry": {
                "type": "Point",
                "coordinates": [
                    120.15238034000001,
                    23.3782854085
                ]
            }
        },
        {
            "type": "Feature",
            "properties": {
                "code": "074603",
                "count": 1
            },
            "geometry": {
                "type": "Point",
                "coordinates": [
                    120.533369765,
                    24.071259367499998
                ]
            }
        },
        {
            "type": "Feature",
            "properties": {
                "code": "154678",
                "count": 1
            },
            "geometry": {
                "type": "Point",
                "coordinates": [
                    121.266723035,
                    23.154644064499998
                ]
            }
        },
        {
            "type": "Feature",
            "properties": {
                "code": "164507",
                "count": 13
            },
            "geometry": {
                "type": "Point",
                "coordinates": [
                    119.5975473,
                    23.667861277
                ]
            }
        },
        {
            "type": "Feature",
            "properties": {
                "code": "154622",
                "count": 7
            },
            "geometry": {
                "type": "Point",
                "coordinates": [
                    121.57814841000001,
                    23.935849748
                ]
            }
        },
        {
            "type": "Feature",
            "properties": {
                "code": "044501",
                "count": 2
            },
            "geometry": {
                "type": "Point",
                "coordinates": [
                    121.08557141,
                    24.7355946275
                ]
            }
        },
        {
            "type": "Feature",
            "properties": {
                "code": "164615",
                "count": 2
            },
            "geometry": {
                "type": "Point",
                "coordinates": [
                    119.65122887000001,
                    23.5831144565
                ]
            }
        },
        {
            "type": "Feature",
            "properties": {
                "code": "164505",
                "count": 22
            },
            "geometry": {
                "type": "Point",
                "coordinates": [
                    119.61140622,
                    23.590281679500002
                ]
            }
        },
        {
            "type": "Feature",
            "properties": {
                "code": "134536",
                "count": 2
            },
            "geometry": {
                "type": "Point",
                "coordinates": [
                    120.77596474500001,
                    22.1288872265
                ]
            }
        },
        {
            "type": "Feature",
            "properties": {
                "code": "024622",
                "count": 1
            },
            "geometry": {
                "type": "Point",
                "coordinates": [
                    121.83321000000001,
                    24.640435
                ]
            }
        },
        {
            "type": "Feature",
            "properties": {
                "code": "164625",
                "count": 5
            },
            "geometry": {
                "type": "Point",
                "coordinates": [
                    119.597656545,
                    23.6658684465
                ]
            }
        },
        {
            "type": "Feature",
            "properties": {
                "code": "134725",
                "count": 4
            },
            "geometry": {
                "type": "Point",
                "coordinates": [
                    120.73037353,
                    22.076014021
                ]
            }
        },
        {
            "type": "Feature",
            "properties": {
                "code": "154687",
                "count": 1
            },
            "geometry": {
                "type": "Point",
                "coordinates": [
                    121.59915091,
                    24.0536813595
                ]
            }
        },
        {
            "type": "Feature",
            "properties": {
                "code": "044638",
                "count": 1
            },
            "geometry": {
                "type": "Point",
                "coordinates": [
                    121.0389308,
                    24.926994299
                ]
            }
        },
        {
            "type": "Feature",
            "properties": {
                "code": "144636",
                "count": 2
            },
            "geometry": {
                "type": "Point",
                "coordinates": [
                    120.888650125,
                    22.339849361
                ]
            }
        },
        {
            "type": "Feature",
            "properties": {
                "code": "154693",
                "count": 2
            },
            "geometry": {
                "type": "Point",
                "coordinates": [
                    121.412875,
                    23.705675
                ]
            }
        },
        {
            "type": "Feature",
            "properties": {
                "code": "104647",
                "count": 1
            },
            "geometry": {
                "type": "Point",
                "coordinates": [
                    120.15257574,
                    23.466498498
                ]
            }
        },
        {
            "type": "Feature",
            "properties": {
                "code": "104502",
                "count": 1
            },
            "geometry": {
                "type": "Point",
                "coordinates": [
                    120.25107951,
                    23.467287013
                ]
            }
        },
        {
            "type": "Feature",
            "properties": {
                "code": "024505",
                "count": 1
            },
            "geometry": {
                "type": "Point",
                "coordinates": [
                    121.76635999999999,
                    24.67174
                ]
            }
        },
        {
            "type": "Feature",
            "properties": {
                "code": "024655",
                "count": 2
            },
            "geometry": {
                "type": "Point",
                "coordinates": [
                    121.806625,
                    24.62883
                ]
            }
        },
        {
            "type": "Feature",
            "properties": {
                "code": "134681",
                "count": 1
            },
            "geometry": {
                "type": "Point",
                "coordinates": [
                    120.590123245,
                    22.3683436545
                ]
            }
        },
        {
            "type": "Feature",
            "properties": {
                "code": "024674",
                "count": 17
            },
            "geometry": {
                "type": "Point",
                "coordinates": [
                    121.77827500000001,
                    24.445635
                ]
            }
        },
        {
            "type": "Feature",
            "properties": {
                "code": "074526",
                "count": 2
            },
            "geometry": {
                "type": "Point",
                "coordinates": [
                    120.550022345,
                    24.02997283
                ]
            }
        },
        {
            "type": "Feature",
            "properties": {
                "code": "164641",
                "count": 3
            },
            "geometry": {
                "type": "Point",
                "coordinates": [
                    119.322662855,
                    23.4000361515
                ]
            }
        },
        {
            "type": "Feature",
            "properties": {
                "code": "714502",
                "count": 28
            },
            "geometry": {
                "type": "Point",
                "coordinates": [
                    118.42194296,
                    24.4367624655
                ]
            }
        },
        {
            "type": "Feature",
            "properties": {
                "code": "144669",
                "count": 3
            },
            "geometry": {
                "type": "Point",
                "coordinates": [
                    121.451932865,
                    23.3162264255
                ]
            }
        },
        {
            "type": "Feature",
            "properties": {
                "code": "144518",
                "count": 2
            },
            "geometry": {
                "type": "Point",
                "coordinates": [
                    121.459326885,
                    23.314777771000003
                ]
            }
        },
        {
            "type": "Feature",
            "properties": {
                "code": "144664",
                "count": 1
            },
            "geometry": {
                "type": "Point",
                "coordinates": [
                    121.33030582,
                    23.026659007
                ]
            }
        },
        {
            "type": "Feature",
            "properties": {
                "code": "024609",
                "count": 1
            },
            "geometry": {
                "type": "Point",
                "coordinates": [
                    121.742365,
                    24.754555
                ]
            }
        },
        {
            "type": "Feature",
            "properties": {
                "code": "024672",
                "count": 1
            },
            "geometry": {
                "type": "Point",
                "coordinates": [
                    121.80040500000001,
                    24.467129999999997
                ]
            }
        },
        {
            "type": "Feature",
            "properties": {
                "code": "054532",
                "count": 2
            },
            "geometry": {
                "type": "Point",
                "coordinates": [
                    120.90277738500001,
                    24.6984886785
                ]
            }
        },
        {
            "type": "Feature",
            "properties": {
                "code": "134759",
                "count": 6
            },
            "geometry": {
                "type": "Point",
                "coordinates": [
                    120.627298255,
                    22.369866579
                ]
            }
        },
        {
            "type": "Feature",
            "properties": {
                "code": "144696",
                "count": 1
            },
            "geometry": {
                "type": "Point",
                "coordinates": [
                    121.146768635,
                    23.04461475
                ]
            }
        },
        {
            "type": "Feature",
            "properties": {
                "code": "144519",
                "count": 1
            },
            "geometry": {
                "type": "Point",
                "coordinates": [
                    121.08055584499999,
                    22.902946876
                ]
            }
        },
        {
            "type": "Feature",
            "properties": {
                "code": "154699",
                "count": 3
            },
            "geometry": {
                "type": "Point",
                "coordinates": [
                    121.34459632,
                    23.438764704999997
                ]
            }
        },
        {
            "type": "Feature",
            "properties": {
                "code": "144656",
                "count": 5
            },
            "geometry": {
                "type": "Point",
                "coordinates": [
                    121.227128135,
                    22.8778775585
                ]
            }
        },
        {
            "type": "Feature",
            "properties": {
                "code": "164514",
                "count": 3
            },
            "geometry": {
                "type": "Point",
                "coordinates": [
                    119.661263245,
                    23.660157079500003
                ]
            }
        },
        {
            "type": "Feature",
            "properties": {
                "code": "144508",
                "count": 2
            },
            "geometry": {
                "type": "Point",
                "coordinates": [
                    121.134631825,
                    22.9070234835
                ]
            }
        },
        {
            "type": "Feature",
            "properties": {
                "code": "074503",
                "count": 1
            },
            "geometry": {
                "type": "Point",
                "coordinates": [
                    120.46875142,
                    24.0976372215
                ]
            }
        },
        {
            "type": "Feature",
            "properties": {
                "code": "144618",
                "count": 1
            },
            "geometry": {
                "type": "Point",
                "coordinates": [
                    121.194124875,
                    22.795796725000002
                ]
            }
        },
        {
            "type": "Feature",
            "properties": {
                "code": "154514",
                "count": 1
            },
            "geometry": {
                "type": "Point",
                "coordinates": [
                    121.38445484,
                    23.588649912
                ]
            }
        },
        {
            "type": "Feature",
            "properties": {
                "code": "154607",
                "count": 1
            },
            "geometry": {
                "type": "Point",
                "coordinates": [
                    121.6188777,
                    24.006961563
                ]
            }
        },
        {
            "type": "Feature",
            "properties": {
                "code": "104652",
                "count": 2
            },
            "geometry": {
                "type": "Point",
                "coordinates": [
                    120.21407962,
                    23.463603002
                ]
            }
        },
        {
            "type": "Feature",
            "properties": {
                "code": "104613",
                "count": 1
            },
            "geometry": {
                "type": "Point",
                "coordinates": [
                    120.17388546500001,
                    23.343071356499998
                ]
            }
        },
        {
            "type": "Feature",
            "properties": {
                "code": "074766",
                "count": 1
            },
            "geometry": {
                "type": "Point",
                "coordinates": [
                    120.34517596500001,
                    23.9787655975
                ]
            }
        },
        {
            "type": "Feature",
            "properties": {
                "code": "134762",
                "count": 1
            },
            "geometry": {
                "type": "Point",
                "coordinates": [
                    120.70704119,
                    22.199711759
                ]
            }
        },
        {
            "type": "Feature",
            "properties": {
                "code": "134537",
                "count": 6
            },
            "geometry": {
                "type": "Point",
                "coordinates": [
                    120.700640255,
                    22.204731141
                ]
            }
        },
        {
            "type": "Feature",
            "properties": {
                "code": "144646",
                "count": 1
            },
            "geometry": {
                "type": "Point",
                "coordinates": [
                    121.155525825,
                    22.95753415
                ]
            }
        },
        {
            "type": "Feature",
            "properties": {
                "code": "164619",
                "count": 1
            },
            "geometry": {
                "type": "Point",
                "coordinates": [
                    119.63610194,
                    23.5640729355
                ]
            }
        },
        {
            "type": "Feature",
            "properties": {
                "code": "074308",
                "count": 4
            },
            "geometry": {
                "type": "Point",
                "coordinates": [
                    120.55525782000001,
                    24.0783420845
                ]
            }
        },
        {
            "type": "Feature",
            "properties": {
                "code": "074764",
                "count": 1
            },
            "geometry": {
                "type": "Point",
                "coordinates": [
                    120.38430474500001,
                    24.0064896115
                ]
            }
        },
        {
            "type": "Feature",
            "properties": {
                "code": "144697",
                "count": 2
            },
            "geometry": {
                "type": "Point",
                "coordinates": [
                    121.20670109,
                    23.149525648500003
                ]
            }
        },
        {
            "type": "Feature",
            "properties": {
                "code": "164503",
                "count": 12
            },
            "geometry": {
                "type": "Point",
                "coordinates": [
                    119.589516035,
                    23.5264779325
                ]
            }
        },
        {
            "type": "Feature",
            "properties": {
                "code": "134724",
                "count": 1
            },
            "geometry": {
                "type": "Point",
                "coordinates": [
                    120.824549205,
                    21.928351083
                ]
            }
        },
        {
            "type": "Feature",
            "properties": {
                "code": "104625",
                "count": 1
            },
            "geometry": {
                "type": "Point",
                "coordinates": [
                    120.420088575,
                    23.5276140245
                ]
            }
        },
        {
            "type": "Feature",
            "properties": {
                "code": "164607",
                "count": 1
            },
            "geometry": {
                "type": "Point",
                "coordinates": [
                    119.61762005,
                    23.5493676735
                ]
            }
        },
        {
            "type": "Feature",
            "properties": {
                "code": "024507",
                "count": 2
            },
            "geometry": {
                "type": "Point",
                "coordinates": [
                    121.821947505,
                    24.8646901395
                ]
            }
        },
        {
            "type": "Feature",
            "properties": {
                "code": "154519",
                "count": 3
            },
            "geometry": {
                "type": "Point",
                "coordinates": [
                    121.521168295,
                    23.600689388
                ]
            }
        },
        {
            "type": "Feature",
            "properties": {
                "code": "164506",
                "count": 1
            },
            "geometry": {
                "type": "Point",
                "coordinates": [
                    119.59642746,
                    23.6437726465
                ]
            }
        },
        {
            "type": "Feature",
            "properties": {
                "code": "024504",
                "count": 1
            },
            "geometry": {
                "type": "Point",
                "coordinates": [
                    121.76735,
                    24.68254
                ]
            }
        },
        {
            "type": "Feature",
            "properties": {
                "code": "044517",
                "count": 1
            },
            "geometry": {
                "type": "Point",
                "coordinates": [
                    121.00860267499999,
                    24.750127702500002
                ]
            }
        }
    ]
}