{
    "treeList": [],
    "treeDistinctList": [
        {
            "name": "0328",
            "id": null,
            "count": 20,
            "percent": 24.1
        },
        {
            "name": "0041",
            "id": null,
            "count": 12,
            "percent": 14.5
        },
        {
            "name": "0161",
            "id": null,
            "count": 12,
            "percent": 14.5
        },
        {
            "name": "0222",
            "id": null,
            "count": 9,
            "percent": 10.8
        },
        {
            "name": "0437",
            "id": null,
            "count": 4,
            "percent": 4.8
        },
        {
            "name": "0174",
            "id": null,
            "count": 3,
            "percent": 3.6
        },
        {
            "name": "0193",
            "id": null,
            "count": 2,
            "percent": 2.4
        },
        {
            "name": "0053",
            "id": null,
            "count": 2,
            "percent": 2.4
        },
        {
            "name": "0381",
            "id": null,
            "count": 2,
            "percent": 2.4
        },
        {
            "name": "0320",
            "id": null,
            "count": 2,
            "percent": 2.4
        },
        {
            "name": "0312",
            "id": null,
            "count": 2,
            "percent": 2.4
        },
        {
            "name": "0140",
            "id": null,
            "count": 2,
            "percent": 2.4
        },
        {
            "name": "0333",
            "id": null,
            "count": 1,
            "percent": 1.2
        },
        {
            "name": "0314",
            "id": null,
            "count": 1,
            "percent": 1.2
        },
        {
            "name": "0268",
            "id": null,
            "count": 1,
            "percent": 1.2
        },
        {
            "name": "0194",
            "id": null,
            "count": 1,
            "percent": 1.2
        },
        {
            "name": "0306",
            "id": null,
            "count": 1,
            "percent": 1.2
        },
        {
            "name": "0230",
            "id": null,
            "count": 1,
            "percent": 1.2
        },
        {
            "name": "0213",
            "id": null,
            "count": 1,
            "percent": 1.2
        },
        {
            "name": "0106",
            "id": null,
            "count": 1,
            "percent": 1.2
        },
        {
            "name": "0075",
            "id": null,
            "count": 1,
            "percent": 1.2
        },
        {
            "name": "0389",
            "id": null,
            "count": 1,
            "percent": 1.2
        },
        {
            "name": "0024",
            "id": null,
            "count": 1,
            "percent": 1.2
        }
    ],
    "hasInfoCard": false,
    "treeCount": 83,
    "treeBound": {
        "xmax": 120.77740203,
        "xmin": 120.77599374,
        "ymax": 24.522420917,
        "ymin": 24.521515574
    },
    "choropleth": null,
    "searchPara": {
        "city": "7",
        "town": "7",
        "school": "054647",
        "treeType": null,
        "no": null
    }
}